gyjd/__init__.py
gyjd/config.py
gyjd/event_bus.py
gyjd/exceptions.py
gyjd/cli/__init__.py
gyjd/cli/__main__.py
gyjd/cli/apps/__init__.py
gyjd/cli/apps/jobs/__init__.py
gyjd/cli/apps/jobs/app.py
gyjd/cli/apps/jobs/repos/gyjd_scripts.py
gyjd/core/__init__.py
gyjd/core/config_loader.py
gyjd/core/gyjd_callable.py
gyjd/core/logger.py
gyjd/core/simple_injector.py
gyjd/database/__init__.py
gyjd/database/connection_factory.py
gyjd/database/sqlite_connection.py
gyjd-0.1.0.dev12.dist-info/METADATA
gyjd-0.1.0.dev12.dist-info/WHEEL
gyjd-0.1.0.dev12.dist-info/entry_points.txt
gyjd-0.1.0.dev12.dist-info/RECORD
