Metadata-Version: 2.3
Name: gyjd
Version: 0.1.0.dev12
Summary: Add your description here
Requires-Python: >=3.11
Provides-Extra: cli
Requires-Dist: typer; extra == 'cli'
Requires-Dist: uv; extra == 'cli'
